confscript/__init__.py
confscript-1.5.dist-info/METADATA
confscript-1.5.dist-info/WHEEL
confscript-1.5.dist-info/top_level.txt
confscript-1.5.dist-info/RECORD
