Metadata-Version: 2.1
Name: confscript
Version: 1.5
Summary: A configuration definition language
Home-page: https://github.com/Whirlpool-Programmer/confscript
Author: Whirlpool-Programmer
Author-email: whirlpool.programmer@outlook.com
License: GNU General Public License v3 (GPLv3)
Platform: UNKNOWN
Classifier: Programming Language :: Python :: 3
Classifier: License :: OSI Approved :: GNU General Public License v3 (GPLv3)
Classifier: Operating System :: OS Independent
